jinx/__init__.py
jinx/base.py
jinx/exceptions.py
jinx/stock.py
jinx-1.1.2.dist-info/AUTHORS.rst
jinx-1.1.2.dist-info/LICENSE.txt
jinx-1.1.2.dist-info/METADATA
jinx-1.1.2.dist-info/WHEEL
jinx-1.1.2.dist-info/top_level.txt
jinx-1.1.2.dist-info/RECORD
