Metadata-Version: 2.1
Name: jinx
Version: 1.1.2
Summary: An SDK for getting JSON objects using the IEX Cloud API.
Home-page: https://github.com/brettelliot/jinx
Author: Brett Elliot
Author-email: brett@theelliots.net
License: mit
Project-URL: Documentation, https://github.com/brettelliot/jinx
Platform: any
Classifier: Development Status :: 4 - Beta
Classifier: Programming Language :: Python
Requires-Dist: requests
Provides-Extra: testing
Requires-Dist: pytest ; extra == 'testing'
Requires-Dist: pytest-cov ; extra == 'testing'
